audio_metatag.py
audio_metatag-0.1.6.dist-info/licenses/LICENSE
audio_metatag-0.1.6.dist-info/METADATA
audio_metatag-0.1.6.dist-info/WHEEL
audio_metatag-0.1.6.dist-info/entry_points.txt
audio_metatag-0.1.6.dist-info/top_level.txt
audio_metatag-0.1.6.dist-info/RECORD
