Metadata-Version: 2.4
Name: audio-metatag
Version: 0.1.6
Summary: Clean metadata and tag audio files (MP3, FLAC, Ogg Vorbis)
Author: Corey Goldberg
Maintainer: Corey Goldberg
License-Expression: MIT
Project-URL: homepage, https://github.com/cgoldberg/audio-metatag
Project-URL: source, https://github.com/cgoldberg/audio-metatag
Project-URL: download, https://pypi.org/project/audio-metatag
Keywords: audio,cleaner,cli,flac,metadata,mp3,music,ogg-vorbis,tags,tagging
Classifier: Environment :: Console
Classifier: Programming Language :: Python
Classifier: Programming Language :: Python :: 3
Classifier: Programming Language :: Python :: 3.12
Classifier: Programming Language :: Python :: 3.13
Classifier: Programming Language :: Python :: 3.14
Requires-Python: >=3.12
License-File: LICENSE
Requires-Dist: mutagen==1.47.0
Dynamic: license-file
